torchao/__init__.py
torchao/_executorch_ops.py
torchao/csrc_meta_ops.py
torchao/ops.py
torchao/utils.py
torchao/_models/__init__.py
torchao/_models/_eval.py
torchao/_models/utils.py
torchao/_models/llama/__init__.py
torchao/_models/llama/eval.py
torchao/_models/llama/generate.py
torchao/_models/llama/model.py
torchao/_models/llama/tokenizer.py
torchao/_models/sam2/__init__.py
torchao/_models/sam2/automatic_mask_generator.py
torchao/_models/sam2/build_sam.py
torchao/_models/sam2/map_tensor.py
torchao/_models/sam2/sam2_image_predictor.py
torchao/_models/sam2/sam2_video_predictor.py
torchao/_models/sam2/modeling/__init__.py
torchao/_models/sam2/modeling/memory_attention.py
torchao/_models/sam2/modeling/memory_encoder.py
torchao/_models/sam2/modeling/position_encoding.py
torchao/_models/sam2/modeling/sam2_base.py
torchao/_models/sam2/modeling/sam2_utils.py
torchao/_models/sam2/modeling/backbones/__init__.py
torchao/_models/sam2/modeling/backbones/hieradet.py
torchao/_models/sam2/modeling/backbones/image_encoder.py
torchao/_models/sam2/modeling/backbones/utils.py
torchao/_models/sam2/modeling/sam/__init__.py
torchao/_models/sam2/modeling/sam/mask_decoder.py
torchao/_models/sam2/modeling/sam/prompt_encoder.py
torchao/_models/sam2/modeling/sam/transformer.py
torchao/_models/sam2/utils/__init__.py
torchao/_models/sam2/utils/amg.py
torchao/_models/sam2/utils/misc.py
torchao/_models/sam2/utils/transforms.py
torchao/core/__init__.py
torchao/core/config.py
torchao/dtypes/__init__.py
torchao/dtypes/_nf4tensor_api.py
torchao/dtypes/affine_quantized_tensor.py
torchao/dtypes/affine_quantized_tensor_ops.py
torchao/dtypes/nf4tensor.py
torchao/dtypes/utils.py
torchao/dtypes/floatx/__init__.py
torchao/dtypes/floatx/cutlass_semi_sparse_layout.py
torchao/dtypes/floatx/float8_layout.py
torchao/dtypes/floatx/floatx_tensor_core_layout.py
torchao/dtypes/uintx/__init__.py
torchao/dtypes/uintx/bitpacking.py
torchao-0.15.0.dist-info/METADATA
torchao-0.15.0.dist-info/WHEEL
torchao-0.15.0.dist-info/top_level.txt
torchao-0.15.0.dist-info/RECORD
torchao-0.15.0.dist-info/licenses/LICENSE
