Metadata-Version: 2.4
Name: torchao
Version: 0.15.0
Summary: Package for applying ao techniques to GPU models
Home-page: https://github.com/pytorch/ao
License-File: LICENSE
Provides-Extra: dev
Requires-Dist: pytest==8.4.2; extra == "dev"
Requires-Dist: unittest-xml-reporting; extra == "dev"
Requires-Dist: parameterized; extra == "dev"
Requires-Dist: packaging; extra == "dev"
Requires-Dist: transformers; extra == "dev"
Requires-Dist: hypothesis; extra == "dev"
Requires-Dist: sentencepiece; extra == "dev"
Requires-Dist: expecttest; extra == "dev"
Requires-Dist: bitsandbytes; extra == "dev"
Requires-Dist: matplotlib; extra == "dev"
Requires-Dist: pandas; extra == "dev"
Requires-Dist: fire; extra == "dev"
Requires-Dist: tabulate; extra == "dev"
Requires-Dist: tiktoken; extra == "dev"
Requires-Dist: blobfile; extra == "dev"
Requires-Dist: lm_eval; extra == "dev"
Requires-Dist: diskcache; extra == "dev"
Requires-Dist: pycocotools; extra == "dev"
Requires-Dist: tqdm; extra == "dev"
Requires-Dist: importlib_metadata; extra == "dev"
Requires-Dist: ninja; extra == "dev"
Requires-Dist: cmake<4.0.0,>=3.19.0; extra == "dev"
Requires-Dist: ruff==0.11.6; extra == "dev"
Requires-Dist: pre-commit; extra == "dev"
Dynamic: description
Dynamic: description-content-type
Dynamic: home-page
Dynamic: license-file
Dynamic: provides-extra
Dynamic: summary
